README.rst
setup.py
jirathumper/__init__.py
jirathumper/main.py
jirathumper.egg-info/PKG-INFO
jirathumper.egg-info/SOURCES.txt
jirathumper.egg-info/dependency_links.txt
jirathumper.egg-info/entry_points.txt
jirathumper.egg-info/not-zip-safe
jirathumper.egg-info/requires.txt
jirathumper.egg-info/top_level.txt