Metadata-Version: 1.0
Name: jirathumper
Version: 1.0
Summary: Parse JimFlowKlopfer JSON output files and update JIRA. Replaces the PHP cron job in JimFlowWall.
Home-page: UNKNOWN
Author: Martin Aspeli
Author-email: optilude@gmail.com
License: GPL
Keywords: jimflow kanban jira
Platform: UNKNOWN
